sdk_license_client/__init__.py
sdk_license_client/client.cpython-39-darwin.so
sdk_license_client/s.cpython-39-darwin.so
sdk_license_client/protobuf/__init__.py
sdk_license_client/protobuf/license_pb2.cpython-39-darwin.so
sdk_license_client/protobuf/license_pb2_grpc.cpython-39-darwin.so
sdk_license_client-1.0.1.dist-info/LICENSE
sdk_license_client-1.0.1.dist-info/METADATA
sdk_license_client-1.0.1.dist-info/WHEEL
sdk_license_client-1.0.1.dist-info/top_level.txt
sdk_license_client-1.0.1.dist-info/RECORD
